pilight/__init__.py
pilight/__init__.pyc
pilight/pilight.py
pilight/pilight.pyc
pilight/__pycache__/__init__.cpython-35.pyc
pilight/__pycache__/pilight.cpython-35.pyc
pilight/tests/__init__.py
pilight/tests/__init__.pyc
pilight/tests/test_client.py
pilight/tests/test_client.pyc
pilight-0.0.2.dist-info/DESCRIPTION.rst
pilight-0.0.2.dist-info/METADATA
pilight-0.0.2.dist-info/RECORD
pilight-0.0.2.dist-info/WHEEL
pilight-0.0.2.dist-info/metadata.json
pilight-0.0.2.dist-info/top_level.txt
