Metadata-Version: 2.0
Name: pilight
Version: 0.0.2
Summary: A pure python module to connect to a pilight daemon to send and receive commands.
Home-page: https://github.com/DavidLP/pilight
Author: David-Leon Pohl
Author-email: David-Leon.Pohl@rub.de
License: MIT License
Keywords: pilight,433,light
Platform: any
